freelens.py
freelens-0.0.2.dist-info/LICENSE
freelens-0.0.2.dist-info/WHEEL
freelens-0.0.2.dist-info/METADATA
freelens-0.0.2.dist-info/RECORD
