Metadata-Version: 2.3
Name: freelens
Version: 0.0.2
Summary: Reference implementation of NaviLens and ddTag
Author-email: Stephen Tierney <sjtrny@gmail.com>
Requires-Python: >=3.11
Requires-Dist: crc==7.1.0
Requires-Dist: numpy==2.0.0
Requires-Dist: opencv-python==4.10.0.84
Requires-Dist: Pillow==11.0.0
Project-URL: Home, https://github.com/sjtrny/freelens
